rzodkiewka/__init__.py
rzodkiewka/rzodkiewka.py
rzodkiewka/cve/__init__.py
rzodkiewka/cve/cve_list.py
rzodkiewka/cve/downloader.py
rzodkiewka/cve/simplifier.py
rzodkiewka/cve/splitter.py
rzodkiewka/cwe/__init__.py
rzodkiewka/cwe/downloader.py
rzodkiewka/cwe/simplifier.py
rzodkiewka/helpers/__init__.py
rzodkiewka/helpers/utils.py
rzodkiewka-0.0.8.dist-info/LICENSE
rzodkiewka-0.0.8.dist-info/METADATA
rzodkiewka-0.0.8.dist-info/WHEEL
rzodkiewka-0.0.8.dist-info/top_level.txt
rzodkiewka-0.0.8.dist-info/RECORD
